jetblack_graphql_types/__init__.py
jetblack_graphql_types/datetime_type.py
jetblack_graphql_types/duration_type.py
jetblack_graphql_types/json_type.py
jetblack_graphql_types/long_type.py
jetblack_graphql_types/py.typed
jetblack_graphql_types-0.2.0.dist-info/LICENSE
jetblack_graphql_types-0.2.0.dist-info/WHEEL
jetblack_graphql_types-0.2.0.dist-info/METADATA
jetblack_graphql_types-0.2.0.dist-info/RECORD
